LICENSE
README.md
setup.py
adatest/__init__.py
adatest/_model.py
adatest/_prompt_builder.py
adatest/_scorer.py
adatest/_server.py
adatest/_test_tree.py
adatest/_test_tree_browser.py
adatest/_topic_model.py
adatest/comm.py
adatest/embedders.py
adatest/generators.py
adatest.egg-info/PKG-INFO
adatest.egg-info/SOURCES.txt
adatest.egg-info/dependency_links.txt
adatest.egg-info/requires.txt
adatest.egg-info/top_level.txt
adatest/resources/favicon.png
adatest/resources/main.js
adatest/resources/main.js.LICENSE.txt
adatest/utils/__init__.py